django_bs/__init__.py
django_bs/templates/bs/field.html
django_bs/templates/bs/form.html
django_bs/templates/bs/messages.html
django_bs/templates/bs/pagination.html
django_bs/templates/django/forms/default.html
django_bs/templates/django/forms/div.html
django_bs/templates/django/forms/field.html
django_bs/templates/django/forms/widgets/checkbox.html
django_bs/templates/django/forms/widgets/checkbox_option.html
django_bs/templates/django/forms/widgets/clearable_file_input.html
django_bs/templates/django/forms/widgets/input.html
django_bs/templates/django/forms/widgets/multiple_input.html
django_bs/templates/django/forms/widgets/multiwidget.html
django_bs/templates/django/forms/widgets/radio_option.html
django_bs/templates/django/forms/widgets/select.html
django_bs/templates/django/forms/widgets/textarea.html
django_bs/templatetags/__init__.py
django_bs/templatetags/bootstrap.py
django_bs-5.4.1.dist-info/licenses/LICENSE
django_bs-5.4.1.dist-info/METADATA
django_bs-5.4.1.dist-info/WHEEL
django_bs-5.4.1.dist-info/top_level.txt
django_bs-5.4.1.dist-info/RECORD
