Metadata-Version: 2.4
Name: django-bs
Version: 5.4.1
Summary: simple bootstrap support for django
Author-email: Tobias Bengfort <tobias.bengfort@posteo.de>
License-Expression: MIT
Project-URL: Homepage, https://github.com/xi/django-bs
Classifier: Intended Audience :: Developers
Classifier: Environment :: Web Environment
Classifier: Framework :: Django
License-File: LICENSE
Dynamic: license-file
